tdmgr/__init__.py
tdmgr/_version.py
tdmgr/mqtt.py
tdmgr/run.py
tdmgr/GUI/__init__.py
tdmgr/GUI/common.py
tdmgr/GUI/console.py
tdmgr/GUI/devices.py
tdmgr/GUI/icons.py
tdmgr/GUI/rules.py
tdmgr/GUI/telemetry.py
tdmgr/GUI/widgets.py
tdmgr/GUI/delegates/__init__.py
tdmgr/GUI/delegates/devices.py
tdmgr/GUI/dialogs/__init__.py
tdmgr/GUI/dialogs/broker.py
tdmgr/GUI/dialogs/bssid.py
tdmgr/GUI/dialogs/buttons.py
tdmgr/GUI/dialogs/clear_lwt.py
tdmgr/GUI/dialogs/gpio.py
tdmgr/GUI/dialogs/main.py
tdmgr/GUI/dialogs/modules.py
tdmgr/GUI/dialogs/patterns.py
tdmgr/GUI/dialogs/power.py
tdmgr/GUI/dialogs/prefs.py
tdmgr/GUI/dialogs/setoptions.py
tdmgr/GUI/dialogs/switches.py
tdmgr/GUI/dialogs/templates.py
tdmgr/GUI/dialogs/timers.py
tdmgr/models/__init__.py
tdmgr/models/devices.py
tdmgr/models/roles.py
tdmgr/schemas/__init__.py
tdmgr/schemas/common.py
tdmgr/schemas/discovery.py
tdmgr/schemas/result.py
tdmgr/schemas/rules.py
tdmgr/schemas/status.py
tdmgr/tasmota/__init__.py
tdmgr/tasmota/commands.py
tdmgr/tasmota/common.py
tdmgr/tasmota/device.py
tdmgr/tasmota/discovery.py
tdmgr/tasmota/environment.py
tdmgr/tasmota/setoptions.py
tdmgr-2024.9.3.dist-info/LICENSE
tdmgr-2024.9.3.dist-info/METADATA
tdmgr-2024.9.3.dist-info/WHEEL
tdmgr-2024.9.3.dist-info/entry_points.txt
tdmgr-2024.9.3.dist-info/top_level.txt
tdmgr-2024.9.3.dist-info/RECORD
