Metadata-Version: 2.1
Name: tdmgr
Version: 2024.9.3
Summary: Tasmota Device Manager is able to find, monitor and do magic things. Like a Superhero.
Author-email: jziolkowski <jacek@ziolkowscy.com>
License: GNU GENERAL PUBLIC LICENSE
Project-URL: homepage, https://github.com/jziolkowski/tdm
Project-URL: issue-tracker, https://github.com/jziolkowski/tdm/issues
Project-URL: documentation, https://github.com/jziolkowski/tdm/wiki
Keywords: Tasmota,Device Manager,Home Automation
Classifier: Programming Language :: Python :: 3.8
Classifier: Programming Language :: Python :: 3.9
Classifier: License :: OSI Approved :: GNU General Public License v3 (GPLv3)
Classifier: Operating System :: OS Independent
Classifier: Topic :: Home Automation
Classifier: Development Status :: 4 - Beta
Requires-Python: >=3.8
License-File: LICENSE
Requires-Dist: paho-mqtt <2,>=1.4
Requires-Dist: PyQt5 <6,>=5.14.2
Requires-Dist: pydantic ==2.5.2
